setup.py
gaussian_dist/Binomialdistribution.py
gaussian_dist/Gaussiandistribution.py
gaussian_dist/Generaldistribution.py
gaussian_dist/__init__.py
gaussian_dist.egg-info/PKG-INFO
gaussian_dist.egg-info/SOURCES.txt
gaussian_dist.egg-info/dependency_links.txt
gaussian_dist.egg-info/not-zip-safe
gaussian_dist.egg-info/top_level.txt