Metadata-Version: 1.0
Name: gaussian-dist
Version: 1.0
Summary: Gaussian and Binomial distributions
Home-page: UNKNOWN
Author: Aditya Bisoi
Author-email: UNKNOWN
License: UNKNOWN
Platform: UNKNOWN
